InputUtils/__init__.py
InputUtils/input_utils.py
InputUtilsSidd-1.1.5.dist-info/METADATA
InputUtilsSidd-1.1.5.dist-info/WHEEL
InputUtilsSidd-1.1.5.dist-info/top_level.txt
InputUtilsSidd-1.1.5.dist-info/RECORD
