Metadata-Version: 2.1
Name: InputUtilsSidd
Version: 1.1.5
Summary: Utility functions for interactive user input handling.
Author: Sidd Karthik
